{"Title":["NY Times, Wed, Apr 25, 2018"],"Author":["Adam G. Perl"],"Editor":["Will Shortz"],"Publisher":["The New York Times"],"Date":["4/25/2018"],"Size":[{"Rows":["15"],"Cols":["15"]}],"Grid":[{"Row":["ERGO.MRI..PARAS","TOREOPEN.SILICA","NBADRAFT.FRIGHT","ATT.EAU.SPONGES","..UNS.SMIDGE...",".GIST.EAT.IDAHO","SETFEE.DAD..NOG","KNOWSEVERYANGLE","ORU..REM.ELOISE","RESIN.GAB.IGET.","...CABANA.EOS..","BASETEN.NUN.LEX","ACTSAS.CASEFILE","BUYINS.INSEASON","SPENT..OAR.ATNO"]}],"Shades":[{"Shade":[{"_":"gray","$":{"Row":"1","Col":"13"}},{"_":"gray","$":{"Row":"2","Col":"2"}},{"_":"gray","$":{"Row":"2","Col":"13"}},{"_":"gray","$":{"Row":"3","Col":"2"}},{"_":"gray","$":{"Row":"3","Col":"13"}},{"_":"gray","$":{"Row":"3","Col":"14"}},{"_":"gray","$":{"Row":"3","Col":"15"}},{"_":"gray","$":{"Row":"4","Col":"2"}},{"_":"gray","$":{"Row":"5","Col":"3"}},{"_":"gray","$":{"Row":"6","Col":"4"}},{"_":"gray","$":{"Row":"7","Col":"5"}},{"_":"gray","$":{"Row":"12","Col":"2"}},{"_":"gray","$":{"Row":"12","Col":"4"}},{"_":"gray","$":{"Row":"12","Col":"13"}},{"_":"gray","$":{"Row":"12","Col":"14"}},{"_":"gray","$":{"Row":"12","Col":"15"}},{"_":"gray","$":{"Row":"13","Col":"2"}},{"_":"gray","$":{"Row":"13","Col":"3"}},{"_":"gray","$":{"Row":"13","Col":"12"}},{"_":"gray","$":{"Row":"14","Col":"2"}},{"_":"gray","$":{"Row":"14","Col":"11"}},{"_":"gray","$":{"Row":"15","Col":"10"}}]}],"Clues":[{"Clue":[{"_":"As a result","$":{"Row":"1","Col":"1","Num":"1","Dir":"Across","Ans":"ERGO"}},{"_":"Dr.'s order","$":{"Row":"1","Col":"6","Num":"5","Dir":"Across","Ans":"MRI"}},{"_":"Legal assistants, for short","$":{"Row":"1","Col":"11","Num":"8","Dir":"Across","Ans":"PARAS"}},{"_":"Ripped the wrapping off","$":{"Row":"2","Col":"1","Num":"13","Dir":"Across","Ans":"TOREOPEN"}},{"_":"Glass component","$":{"Row":"2","Col":"10","Num":"15","Dir":"Across","Ans":"SILICA"}},{"_":"Kings' guards may be taken in it","$":{"Row":"3","Col":"1","Num":"16","Dir":"Across","Ans":"NBADRAFT"}},{"_":"Haunted house feeling","$":{"Row":"3","Col":"10","Num":"17","Dir":"Across","Ans":"FRIGHT"}},{"_":"QB's stat: Abbr.","$":{"Row":"4","Col":"1","Num":"18","Dir":"Across","Ans":"ATT"}},{"_":"___ de toilette","$":{"Row":"4","Col":"5","Num":"19","Dir":"Across","Ans":"EAU"}},{"_":"Moochers","$":{"Row":"4","Col":"9","Num":"20","Dir":"Across","Ans":"SPONGES"}},{"_":"Young ___","$":{"Row":"5","Col":"3","Num":"21","Dir":"Across","Ans":"UNS"}},{"_":"Iota","$":{"Row":"5","Col":"7","Num":"23","Dir":"Across","Ans":"SMIDGE"}},{"_":"Essence","$":{"Row":"6","Col":"2","Num":"25","Dir":"Across","Ans":"GIST"}},{"_":"\"Mangia!\"","$":{"Row":"6","Col":"7","Num":"26","Dir":"Across","Ans":"EAT"}},{"_":"Moscow's home","$":{"Row":"6","Col":"11","Num":"27","Dir":"Across","Ans":"IDAHO"}},{"_":"Flat rate","$":{"Row":"7","Col":"1","Num":"31","Dir":"Across","Ans":"SETFEE"}},{"_":"Pops","$":{"Row":"7","Col":"8","Num":"33","Dir":"Across","Ans":"DAD"}},{"_":"Holiday quaff","$":{"Row":"7","Col":"13","Num":"35","Dir":"Across","Ans":"NOG"}},{"_":"Is an expert on this puzzle's theme?","$":{"Row":"8","Col":"1","Num":"36","Dir":"Across","Ans":"KNOWSEVERYANGLE"}},{"_":"Christian inst. in Tulsa","$":{"Row":"9","Col":"1","Num":"40","Dir":"Across","Ans":"ORU"}},{"_":"Sleep stage","$":{"Row":"9","Col":"6","Num":"41","Dir":"Across","Ans":"REM"}},{"_":"Plaza girl in kid-lit","$":{"Row":"9","Col":"10","Num":"42","Dir":"Across","Ans":"ELOISE"}},{"_":"Amber, e.g.","$":{"Row":"10","Col":"1","Num":"43","Dir":"Across","Ans":"RESIN"}},{"_":"It's a gift","$":{"Row":"10","Col":"7","Num":"46","Dir":"Across","Ans":"GAB"}},{"_":"\"___ that a lot\"","$":{"Row":"10","Col":"11","Num":"48","Dir":"Across","Ans":"IGET"}},{"_":"Place to change at the beach","$":{"Row":"11","Col":"4","Num":"49","Dir":"Across","Ans":"CABANA"}},{"_":"Goddess of dawn","$":{"Row":"11","Col":"11","Num":"51","Dir":"Across","Ans":"EOS"}},{"_":"Decimal system","$":{"Row":"12","Col":"1","Num":"52","Dir":"Across","Ans":"BASETEN"}},{"_":"Novice, perhaps","$":{"Row":"12","Col":"9","Num":"55","Dir":"Across","Ans":"NUN"}},{"_":"Big Apple subway line, for short","$":{"Row":"12","Col":"13","Num":"57","Dir":"Across","Ans":"LEX"}},{"_":"Fills in for","$":{"Row":"13","Col":"1","Num":"60","Dir":"Across","Ans":"ACTSAS"}},{"_":"Set of documents on a legal matter","$":{"Row":"13","Col":"8","Num":"61","Dir":"Across","Ans":"CASEFILE"}},{"_":"Amounts paid to join poker games","$":{"Row":"14","Col":"1","Num":"63","Dir":"Across","Ans":"BUYINS"}},{"_":"Like peaches around summer and early fall","$":{"Row":"14","Col":"8","Num":"64","Dir":"Across","Ans":"INSEASON"}},{"_":"Totally wiped","$":{"Row":"15","Col":"1","Num":"65","Dir":"Across","Ans":"SPENT"}},{"_":"Galley item","$":{"Row":"15","Col":"8","Num":"66","Dir":"Across","Ans":"OAR"}},{"_":"Periodic table fig.","$":{"Row":"15","Col":"12","Num":"67","Dir":"Across","Ans":"ATNO"}},{"_":"European smoker","$":{"Row":"1","Col":"1","Num":"1","Dir":"Down","Ans":"ETNA"}},{"_":"Gen. ___ E. Lee","$":{"Row":"1","Col":"2","Num":"2","Dir":"Down","Ans":"ROBT"}},{"_":"Provided but not asked for","$":{"Row":"1","Col":"3","Num":"3","Dir":"Down","Ans":"GRATUITOUS"}},{"_":"Classic work originally in 10 vols.","$":{"Row":"1","Col":"4","Num":"4","Dir":"Down","Ans":"OED"}},{"_":"Film-rating grp.","$":{"Row":"1","Col":"6","Num":"5","Dir":"Down","Ans":"MPAA"}},{"_":"Decline","$":{"Row":"1","Col":"7","Num":"6","Dir":"Down","Ans":"REFUSE"}},{"_":"QB's stat: Abbr.","$":{"Row":"1","Col":"8","Num":"7","Dir":"Down","Ans":"INT"}},{"_":"Ravioli relative","$":{"Row":"1","Col":"11","Num":"8","Dir":"Down","Ans":"PIROGI"}},{"_":"Trued up","$":{"Row":"1","Col":"12","Num":"9","Dir":"Down","Ans":"ALINED"}},{"_":"Diana ___, 1969 Bond girl","$":{"Row":"1","Col":"13","Num":"10","Dir":"Down","Ans":"RIGG"}},{"_":"Long","$":{"Row":"1","Col":"14","Num":"11","Dir":"Down","Ans":"ACHE"}},{"_":"Concerns for many srs.","$":{"Row":"1","Col":"15","Num":"12","Dir":"Down","Ans":"SATS"}},{"_":"Euripides tragedy","$":{"Row":"2","Col":"5","Num":"14","Dir":"Down","Ans":"ORESTES"}},{"_":"Dirty Harry's org.","$":{"Row":"2","Col":"10","Num":"15","Dir":"Down","Ans":"SFPD"}},{"_":"Instrument in \"Norwegian Wood\"","$":{"Row":"4","Col":"9","Num":"20","Dir":"Down","Ans":"SITAR"}},{"_":"Office-inappropriate, briefly","$":{"Row":"5","Col":"4","Num":"22","Dir":"Down","Ans":"NSFW"}},{"_":"Family guy?","$":{"Row":"5","Col":"8","Num":"24","Dir":"Down","Ans":"MADEMAN"}},{"_":"Category","$":{"Row":"6","Col":"2","Num":"25","Dir":"Down","Ans":"GENRE"}},{"_":"Online aid for finding a contractor","$":{"Row":"6","Col":"13","Num":"28","Dir":"Down","Ans":"ANGIESLIST"}},{"_":"Gustav who composed \"The Planets\"","$":{"Row":"6","Col":"14","Num":"29","Dir":"Down","Ans":"HOLST"}},{"_":"Curved molding","$":{"Row":"6","Col":"15","Num":"30","Dir":"Down","Ans":"OGEE"}},{"_":"Toffee candy bar","$":{"Row":"7","Col":"1","Num":"31","Dir":"Down","Ans":"SKOR"}},{"_":"Ending with auction","$":{"Row":"7","Col":"6","Num":"32","Dir":"Down","Ans":"EER"}},{"_":"Indigo, e.g.","$":{"Row":"7","Col":"10","Num":"34","Dir":"Down","Ans":"DYE"}},{"_":"One unlikely to order ham and eggs","$":{"Row":"8","Col":"7","Num":"37","Dir":"Down","Ans":"VEGAN"}},{"_":"Heir, legally","$":{"Row":"8","Col":"11","Num":"38","Dir":"Down","Ans":"ALIENEE"}},{"_":"Scrubbed","$":{"Row":"8","Col":"12","Num":"39","Dir":"Down","Ans":"NOGO"}},{"_":"Strands at a ski chalet, say","$":{"Row":"10","Col":"4","Num":"44","Dir":"Down","Ans":"ICESIN"}},{"_":"Swimming","$":{"Row":"10","Col":"5","Num":"45","Dir":"Down","Ans":"NATANT"}},{"_":"One of a bunch","$":{"Row":"10","Col":"9","Num":"47","Dir":"Down","Ans":"BANANA"}},{"_":"Gershwin heroine","$":{"Row":"11","Col":"6","Num":"50","Dir":"Down","Ans":"BESS"}},{"_":"Streisand, familiarly","$":{"Row":"12","Col":"1","Num":"52","Dir":"Down","Ans":"BABS"}},{"_":"Small bra size","$":{"Row":"12","Col":"2","Num":"53","Dir":"Down","Ans":"ACUP"}},{"_":"Eyelid ailment","$":{"Row":"12","Col":"3","Num":"54","Dir":"Down","Ans":"STYE"}},{"_":"Red letters?","$":{"Row":"12","Col":"10","Num":"56","Dir":"Down","Ans":"USSR"}},{"_":"Musk of SpaceX","$":{"Row":"12","Col":"14","Num":"58","Dir":"Down","Ans":"ELON"}},{"_":"Prefix with phobia","$":{"Row":"12","Col":"15","Num":"59","Dir":"Down","Ans":"XENO"}},{"_":"A.F.L.-___","$":{"Row":"13","Col":"8","Num":"61","Dir":"Down","Ans":"CIO"}},{"_":"\"Towering\" regulatory grp.?","$":{"Row":"13","Col":"12","Num":"62","Dir":"Down","Ans":"FAA"}}]}],"JeffNotes":["<p>This former mathlete was embarrassed to not know what a REFLEX angle was. Relieved to hear that Jim didn&#39;t recognize it either! And then when Jill (who&#39;s much brighter than me) screwed up her face &hellip; huh.</p>\r\n\r\n<p><a href=\"https://en.wikipedia.org/wiki/Angie\"><img alt=\"\" src=\"https://upload.wikimedia.org/wikipedia/en/d/df/Angieslist-logo.png\" style=\"border:1px solid lightgray; float:right; height:60px; margin:6px 0px 6px 12px; width:220px\" title=\"ANGIE looks so similar to ANGLE. Hmm!\" /></a></p>\r\n\r\n<p>Good concept, visually representing the major types of angles, OBTUSE, RIGHT, ACUTE. REFLEX, bah!</p>\r\n\r\n<p>I wanted the revealer to be KNEW ALL THE ANGLES. That would have been perfect. I wasn&#39;t sure if KNOWS EVERY ANGLE was as punchy, although it does seem to be in the language. It&#39;s a minor difference in wording, but it took away some of the impact for me.</p>\r\n\r\n<p>For puzzles like these, it&#39;s so important to make your long fill shine. Without good bonuses, the puzzle can lack meatiness. Adam did well with NBA DRAFT, CASE FILE, GRATUITOUS, ANGIES LIST, MADE MAN. Even BASE TEN and SPONGES as [Moochers] helped out. Overall, meatiness achieved!</p>\r\n\r\n<p>The drawback for puzzles like these is that there are almost always serious compromises around those shaded letters fixed into tight places. Throw on top of it the need to thread in a bunch of strong long fill, and smoothness is usually gonna get whacked.</p>\r\n\r\n<p>I was all ready to say how amazed I was by Adam&#39;s execution around the toughest one, the densely-packed ACUTE. But then I hit NATANT. What an odd word.</p>\r\n\r\n<p>REFLEX is tough because of the X, and ANGIES LIST running through it. See ALIENEE, ATNO, I GET.</p>\r\n\r\n<p>ALINED was the worst for me, caused by the RIGHT constraints. Seems to be a variant of &quot;aligned.&quot; Ick!</p>\r\n\r\n<p>I could have overlooked these wonky trade-offs if the puzzle had felt a tad more spot-on to me. Just the three major angles would have made me feel like I truly did KNOW ALL THE ANGLES. Could have helped smoothify the puzzle, too.</p>"],"ConNotes":["<p>I woke up one morning one day after a night of heavy partying and just didn&#39;t feel RIGHT. I was groggy and feeling OBTUSE with an ACUTE pain in my head. My REFLEX response was to examine every ANGLE and do a 180 to get myself out of this mood. So I decided to create a crossword puzzle &ndash; which finally put me STRAIGHT!</p>"]}